dispie/__init__.py
dispie/paginator/__init__.py
dispie/paginator/paginator.py
dispie/paginator/paginators.py
dispie-0.0.2.dist-info/LICENCE
dispie-0.0.2.dist-info/METADATA
dispie-0.0.2.dist-info/WHEEL
dispie-0.0.2.dist-info/top_level.txt
dispie-0.0.2.dist-info/RECORD
