Metadata-Version: 2.1
Name: dispie
Version: 0.0.2
Summary: 🚀 A fantastic library created for use with Discord.py
Home-page: https://github.com/PranoyMajumdar/dispie
Author: Pranoy Majumdar
Author-email: officialpranoy2@gmail.com
License: MIT
Project-URL: Homepage, https://github.com/PranoyMajumdar/dispie
Classifier: Programming Language :: Python :: 3
Classifier: License :: OSI Approved :: MIT License
Classifier: Operating System :: OS Independent
Requires-Python: >=3.7
License-File: LICENCE
